gen_dedup/__init__.py
gen_dedup/dedup.py
gen_dedup/version.py
gen_dedup/models/__init__.py
gen_dedup/models/modeling_t5.py
gen_dedup-0.0.2.dist-info/LICENSE
gen_dedup-0.0.2.dist-info/METADATA
gen_dedup-0.0.2.dist-info/WHEEL
gen_dedup-0.0.2.dist-info/top_level.txt
gen_dedup-0.0.2.dist-info/RECORD
