Metadata-Version: 2.1
Name: gen-dedup
Version: 0.0.2
Summary: Generative deduplication
Home-page: https://github.com/4AI/generative_deduplication
Author: Sean Lee
Author-email: xmlee97@gmail.com
Classifier: Development Status :: 3 - Alpha
Classifier: Intended Audience :: Developers
Classifier: License :: OSI Approved :: MIT License
Classifier: Operating System :: OS Independent
Classifier: Programming Language :: Python :: 3
Classifier: Programming Language :: Python :: 3.8
Classifier: Programming Language :: Python :: 3.9
Classifier: Programming Language :: Python :: 3.10
Classifier: Programming Language :: Python :: 3.11
Requires-Python: >=3.8
License-File: LICENSE
Requires-Dist: tqdm
Requires-Dist: datasets
Requires-Dist: transformers
